mapmaker/__init__.py
mapmaker/core.py
mapmaker/decorations.py
mapmaker/draw.py
mapmaker/geo.py
mapmaker/geojson.py
mapmaker/icons.py
mapmaker/main.py
mapmaker/mapdef.py
mapmaker/parse.py
mapmaker/render.py
mapmaker/service.py
mapmaker/tilemap.py
mapmaker-1.6.1.dist-info/LICENSE.txt
mapmaker-1.6.1.dist-info/METADATA
mapmaker-1.6.1.dist-info/WHEEL
mapmaker-1.6.1.dist-info/entry_points.txt
mapmaker-1.6.1.dist-info/top_level.txt
mapmaker-1.6.1.dist-info/RECORD
