Metadata-Version: 2.1
Name: mapmaker
Version: 1.6.1
Summary: Create map images from slippy map tiles.
Home-page: http://github.com/akeil/mapmaker
Author: Alexander Keil
Author-email: alex@akeil.net
Maintainer: Alexander Keil
License: MIT
Project-URL: Source, http://github.com/akeil/mapmaker
Project-URL: Bug Reports, http://github.com/akeil/mapmaker/issues
Keywords: osm,openstreetmap,tiles,map,image,cli
Classifier: Development Status :: 4 - Beta
Classifier: Intended Audience :: Developers
Classifier: License :: OSI Approved :: MIT License
Classifier: Programming Language :: Python
Classifier: Programming Language :: Python :: 3
Classifier: Topic :: Scientific/Engineering :: GIS
Classifier: Topic :: Software Development :: Libraries :: Python Modules
Classifier: Topic :: Utilities
Requires-Python: >=3
License-File: LICENSE.txt
Requires-Dist: appdirs
Requires-Dist: Pillow
Requires-Dist: requests
Requires-Dist: geojson
Requires-Dist: cairosvg
Requires-Dist: setuptools
